hetseq/__init__.py
hetseq/bert_modeling.py
hetseq/checkpoint_utils.py
hetseq/controller.py
hetseq/distributed_utils.py
hetseq/eval_bert_fine_tuning_ner.py
hetseq/eval_mnist.py
hetseq/file_utils.py
hetseq/lr_scheduler.py
hetseq/meters.py
hetseq/optim.py
hetseq/options.py
hetseq/progress_bar.py
hetseq/train.py
hetseq/transformers_tasks.py
hetseq/utils.py
hetseq/data/BERT_DATA.py
hetseq/data/BERT_DATA_test.py
hetseq/data/__init__.py
hetseq/data/bert_el_dataset.py
hetseq/data/bert_ner_dataset.py
hetseq/data/data_utils.py
hetseq/data/data_utils_fast.cpython-38-darwin.so
hetseq/data/h5pyDataset.py
hetseq/data/iterators.py
hetseq/data/mnist_dataset.py
hetseq/data_collator/__init__.py
hetseq/data_collator/data_collator.py
hetseq/model/__init__.py
hetseq/model/bert_for_EL_classification.py
hetseq/tasks/__init__.py
hetseq/tasks/bert_for_el_classification_task.py
hetseq/tasks/bert_for_token_classification_task.py
hetseq/tasks/tasks.py
hetseq-1.0.2.dist-info/LICENSE
hetseq-1.0.2.dist-info/METADATA
hetseq-1.0.2.dist-info/WHEEL
hetseq-1.0.2.dist-info/top_level.txt
hetseq-1.0.2.dist-info/RECORD
