Metadata-Version: 2.1
Name: hetseq
Version: 1.0.2
Summary: Distributed GPU Training on Heterogeneous Infrastructureg
Home-page: https://github.com/yifding/hetseq
Author: Yifan Ding
Author-email: dyf0125@gmail.com
License: UNKNOWN
Project-URL: Documentation, https://hetseq.readthedocs.io
Project-URL: Medium Post, https://towardsdatascience.com/training-bert-at-a-university-eedcf940c754
Platform: UNKNOWN
Requires-Dist: cython
Requires-Dist: numpy
Requires-Dist: h5py (==2.10.0)
Requires-Dist: torch (==1.6.0)
Requires-Dist: tqdm (==4.36.1)
Requires-Dist: chardet (==3.0.4)
Requires-Dist: idna (==2.8)
Requires-Dist: python-dateutil (==2.8.0)
Requires-Dist: sphinx-rtd-theme (==0.5.0)
Requires-Dist: sphinx (==3.2.1)
Requires-Dist: boto3 (==1.9.244)
Requires-Dist: torchvision (==0.7.0)
Requires-Dist: datasets (==1.1.3)
Requires-Dist: transformers (==4.1.1)
Requires-Dist: seqeval (==1.2.2)
